embedly/__init__.py
embedly/client.py
embedly/models.py
embedly/tests.py
embedly2-0.6.0.dist-info/LICENSE
embedly2-0.6.0.dist-info/METADATA
embedly2-0.6.0.dist-info/WHEEL
embedly2-0.6.0.dist-info/top_level.txt
embedly2-0.6.0.dist-info/zip-safe
embedly2-0.6.0.dist-info/RECORD
