Metadata-Version: 2.1
Name: embedly2
Version: 0.6.0
Summary: Python Library for Embedly
Home-page: https://github.com/JelleZijlstra/embedly2
Author: Jelle Zijlstra
Author-email: jelle.zijlstra@gmail.com
License: 
Classifier: Development Status :: 5 - Production/Stable
Classifier: Intended Audience :: Developers
Classifier: Natural Language :: English
Classifier: License :: OSI Approved :: BSD License
Classifier: Operating System :: OS Independent
Classifier: Programming Language :: Python
Classifier: Programming Language :: Python :: 3.6
Classifier: Programming Language :: Python :: 3.7
Classifier: Programming Language :: Python :: 3.8
Classifier: Programming Language :: Python :: 3.9
Classifier: Programming Language :: Python :: 3.10
License-File: LICENSE
Requires-Dist: httplib2
